{
"name": "allWays",
"description": "allWays",
"version": "2",
"minzoom": "0",
"maxzoom": "17",
"center": "11.114044,46.070372,17",
"bounds": "11.004715,45.945349,11.204438,46.154102",
"type": "overlay",
"format": "pbf",
"generator": "tippecanoe v1.36.0",
"generator_options": "tippecanoe -z17 -e allWays --no-tile-compression combined.geojson",
"json": "{\"vector_layers\": [ { \"id\": \"combined\", \"description\": \"\", \"minzoom\": 0, \"maxzoom\": 17, \"fields\": {\"color\": \"String\", \"id\": \"Number\", \"tags\": \"String\", \"type\": \"String\"} } ],\"tilestats\": {\"layerCount\": 1,\"layers\": [{\"layer\": \"combined\",\"count\": 14560,\"geometry\": \"LineString\",\"attributeCount\": 4,\"attributes\": [{\"attribute\": \"color\",\"count\": 1000,\"type\": \"string\",\"values\": [\"#000454\",\"#00048F\",\"#0004EE\",\"#000C15\",\"#000E8D\",\"#001212\",\"#0012D2\",\"#00183F\",\"#001951\",\"#001E5F\",\"#002348\",\"#00267A\",\"#003084\",\"#003125\",\"#00323A\",\"#003B98\",\"#003E7F\",\"#005981\",\"#006607\",\"#006D28\",\"#0070CE\",\"#00744E\",\"#0076E7\",\"#0078FA\",\"#007992\",\"#00800B\",\"#008027\",\"#008121\",\"#008545\",\"#00890E\",\"#008953\",\"#008FF6\",\"#00932D\",\"#009DE3\",\"#00A13C\",\"#00A4B9\",\"#00A568\",\"#00AAC1\",\"#00AAEE\",\"#00AF9E\",\"#00AFCF\",\"#00B421\",\"#00B428\",\"#00B726\",\"#00B83B\",\"#00B896\",\"#00B9DE\",\"#00C3EA\",\"#00C434\",\"#00C8C6\",\"#00CAFC\",\"#00CBB5\",\"#00CE47\",\"#00CEC0\",\"#00CF62\",\"#00D6A1\",\"#00E26D\",\"#00E4A6\",\"#00E7A1\",\"#00E8E5\",\"#00ED4E\",\"#00F11B\",\"#00F608\",\"#00FBFB\",\"#00FCBA\",\"#00FE59\",\"#010B07\",\"#0112F3\",\"#011321\",\"#0119AB\",\"#012112\",\"#012804\",\"#01283F\",\"#012E23\",\"#012E70\",\"#012F2C\",\"#0131CB\",\"#0137FC\",\"#013A87\",\"#013C89\",\"#01488D\",\"#014BAC\",\"#014E8D\",\"#0151E5\",\"#015E55\",\"#015F38\",\"#016849\",\"#016C0E\",\"#01736C\",\"#0173A8\",\"#017B11\",\"#0180E2\",\"#018548\",\"#018AEF\",\"#018D66\",\"#018F99\",\"#0191BE\",\"#01921C\",\"#019ADF\",\"#019AEB\"]},{\"attribute\": \"id\",\"count\": 1000,\"type\": \"number\",\"values\": [100002549,100002551,100010478,100010489,100010492,100011705,100011707,100059525,100269150,100269151,100269152,100269153,100269159,100269162,101012798,101012818,101012825,101012826,101012852,101811606,101811607,101811608,101811609,101811611,101930030,101930031,102189362,102662469,102662470,102689935,102691561,102692417,102692424,102692539,102693353,102693357,102693361,102693366,102693419,102693420,102693421,103119932,103473777,103845984,103845985,103845986,103846467,103847386,103847388,103848856,103849033,103850538,103850617,103850672,103850800,103963655,104058647,104058649,104058650,104146038,104146039,104146042,104146044,104158582,104171334,104296067,104296069,104296070,104365483,104417613,104417636,104417719,104549061,104812155,104813095,104814002,104814857,104814859,104816044,104983827,104983828,104983829,104983830,104983831,104983832,104984271,104984272,104984273,104984274,104984275,105068047,105068051,105068052,105068054,105068057,105068058,105690044,105934310,105934312,105956781],\"min\": 13858908,\"max\": 963458916},{\"attribute\": \"tags\",\"count\": 1000,\"type\": \"string\",\"values\": [\"{\\\"FIXME\\\":\\\"Position extimated\\\",\\\"highway\\\":\\\"pedestrian\\\",\\\"lit\\\":\\\"yes\\\",\\\"name\\\":\\\"Via Torre Verde\\\",\\\"surface\\\":\\\"sett\\\"}\",\"{\\\"FIXME\\\":\\\"controllare\\\",\\\"highway\\\":\\\"unclassified\\\",\\\"layer\\\":\\\"-1\\\",\\\"name\\\":\\\"Via Kempten\\\",\\\"tunnel\\\":\\\"yes\\\"}\",\"{\\\"FIXME\\\":\\\"controllare\\\",\\\"highway\\\":\\\"unclassified\\\",\\\"name\\\":\\\"Via Kempten\\\"}\",\"{\\\"FIXME\\\":\\\"unknown tracktype\\\",\\\"highway\\\":\\\"track\\\"}\",\"{\\\"access\\\":\\\"agricultural\\\",\\\"created_by\\\":\\\"Potlatch 0.10f\\\",\\\"highway\\\":\\\"track\\\",\\\"tracktype\\\":\\\"grade3\\\"}\",\"{\\\"access\\\":\\\"agricultural\\\",\\\"created_by\\\":\\\"Potlatch 0.9c\\\",\\\"highway\\\":\\\"track\\\",\\\"tracktype\\\":\\\"grade2\\\"}\",\"{\\\"access\\\":\\\"agricultural\\\",\\\"highway\\\":\\\"track\\\",\\\"motorcar\\\":\\\"yes\\\",\\\"surface\\\":\\\"asphalt\\\",\\\"tracktype\\\":\\\"grade1\\\"}\",\"{\\\"access\\\":\\\"agricultural\\\",\\\"highway\\\":\\\"track\\\",\\\"motorcar\\\":\\\"yes\\\",\\\"surface\\\":\\\"ground\\\",\\\"tracktype\\\":\\\"grade1\\\"}\",\"{\\\"access\\\":\\\"agricultural\\\",\\\"highway\\\":\\\"track\\\",\\\"motorcar\\\":\\\"yes\\\",\\\"surface\\\":\\\"ground\\\",\\\"tracktype\\\":\\\"grade3\\\"}\",\"{\\\"access\\\":\\\"agricultural\\\",\\\"highway\\\":\\\"track\\\",\\\"name\\\":\\\"Strada di So Ca'\\\",\\\"tracktype\\\":\\\"grade3\\\"}\",\"{\\\"access\\\":\\\"agricultural\\\",\\\"highway\\\":\\\"track\\\",\\\"tracktype\\\":\\\"grade3\\\"}\",\"{\\\"access\\\":\\\"agricultural\\\",\\\"highway\\\":\\\"track\\\",\\\"tracktype\\\":\\\"grade5\\\"}\",\"{\\\"access\\\":\\\"agricultural\\\",\\\"highway\\\":\\\"track\\\"}\",\"{\\\"access\\\":\\\"customers\\\",\\\"highway\\\":\\\"footway\\\",\\\"layer\\\":\\\"-1\\\",\\\"lit\\\":\\\"yes\\\",\\\"location\\\":\\\"underground\\\",\\\"name\\\":\\\"Galleria Bianca\\\",\\\"surface\\\":\\\"paving_stones\\\",\\\"tunnel\\\":\\\"yes\\\"}\",\"{\\\"access\\\":\\\"customers\\\",\\\"highway\\\":\\\"service\\\",\\\"service\\\":\\\"driveway\\\"}\",\"{\\\"access\\\":\\\"delivery\\\",\\\"foot\\\":\\\"yes\\\",\\\"goods\\\":\\\"destination\\\",\\\"highway\\\":\\\"service\\\",\\\"motorcar\\\":\\\"delivery\\\",\\\"name\\\":\\\"Piazzale Europa\\\",\\\"noexit\\\":\\\"yes\\\",\\\"surface\\\":\\\"asphalt\\\"}\",\"{\\\"access\\\":\\\"designated\\\",\\\"highway\\\":\\\"footway\\\",\\\"surface\\\":\\\"gravel\\\"}\",\"{\\\"access\\\":\\\"designated\\\",\\\"highway\\\":\\\"service\\\",\\\"lit\\\":\\\"yes\\\",\\\"maxspeed\\\":\\\"30\\\",\\\"name\\\":\\\"Strada degli Alpini\\\",\\\"surface\\\":\\\"asphalt\\\"}\",\"{\\\"access\\\":\\\"designated\\\",\\\"highway\\\":\\\"track\\\",\\\"surface\\\":\\\"ground\\\",\\\"tracktype\\\":\\\"grade4\\\"}\",\"{\\\"access\\\":\\\"designated\\\",\\\"highway\\\":\\\"track\\\",\\\"tracktype\\\":\\\"grade2\\\"}\",\"{\\\"access\\\":\\\"destination\\\",\\\"bicycle\\\":\\\"yes\\\",\\\"cycleway\\\":\\\"opposite\\\",\\\"foot\\\":\\\"yes\\\",\\\"highway\\\":\\\"residential\\\",\\\"lanes\\\":\\\"1\\\",\\\"lit\\\":\\\"yes\\\",\\\"name\\\":\\\"Via Giannantonio Manci\\\",\\\"old_name\\\":\\\"Via Longa\\\",\\\"oneway\\\":\\\"yes\\\",\\\"oneway:bicycle\\\":\\\"no\\\",\\\"surface\\\":\\\"sett\\\"}\",\"{\\\"access\\\":\\\"destination\\\",\\\"bicycle\\\":\\\"yes\\\",\\\"foot\\\":\\\"yes\\\",\\\"highway\\\":\\\"pedestrian\\\",\\\"lanes\\\":\\\"1\\\",\\\"lit\\\":\\\"yes\\\",\\\"name\\\":\\\"Via Giuseppe Garibaldi\\\",\\\"oneway\\\":\\\"yes\\\",\\\"oneway:bicycle\\\":\\\"no\\\",\\\"surface\\\":\\\"sett\\\"}\",\"{\\\"access\\\":\\\"destination\\\",\\\"bicycle\\\":\\\"yes\\\",\\\"foot\\\":\\\"yes\\\",\\\"highway\\\":\\\"residential\\\",\\\"horse\\\":\\\"yes\\\",\\\"is_in\\\":\\\"Trento, Trentino-Alto Adige, Italy\\\",\\\"name\\\":\\\"Via degli Orti\\\",\\\"oneway\\\":\\\"yes\\\",\\\"oneway:bicycle\\\":\\\"no\\\",\\\"surface\\\":\\\"asphalt\\\"}\",\"{\\\"access\\\":\\\"destination\\\",\\\"bicycle\\\":\\\"yes\\\",\\\"foot\\\":\\\"yes\\\",\\\"highway\\\":\\\"residential\\\",\\\"is_in\\\":\\\"Trento, Trentino-Alto Adige, Italy\\\",\\\"name\\\":\\\"Via Dietro le Mura A\\\",\\\"oneway\\\":\\\"yes\\\",\\\"surface\\\":\\\"asphalt\\\"}\",\"{\\\"access\\\":\\\"destination\\\",\\\"bicycle\\\":\\\"yes\\\",\\\"foot\\\":\\\"yes\\\",\\\"highway\\\":\\\"residential\\\",\\\"lanes\\\":\\\"1\\\",\\\"lit\\\":\\\"yes\\\",\\\"maxspeed\\\":\\\"50\\\",\\\"name\\\":\\\"Via Galileo Galilei\\\",\\\"oneway\\\":\\\"yes\\\",\\\"oneway:bicycle\\\":\\\"no\\\",\\\"surface\\\":\\\"asphalt\\\"}\",\"{\\\"access\\\":\\\"destination\\\",\\\"bicycle\\\":\\\"yes\\\",\\\"foot\\\":\\\"yes\\\",\\\"highway\\\":\\\"residential\\\",\\\"lanes\\\":\\\"1\\\",\\\"lit\\\":\\\"yes\\\",\\\"maxspeed\\\":\\\"50\\\",\\\"name\\\":\\\"Via Roggia Grande\\\",\\\"oneway\\\":\\\"yes\\\",\\\"oneway:bicycle\\\":\\\"no\\\",\\\"surface\\\":\\\"sett\\\"}\",\"{\\\"access\\\":\\\"destination\\\",\\\"bicycle\\\":\\\"yes\\\",\\\"foot\\\":\\\"yes\\\",\\\"highway\\\":\\\"residential\\\",\\\"lanes\\\":\\\"1\\\",\\\"lit\\\":\\\"yes\\\",\\\"maxspeed:type\\\":\\\"IT:urban\\\",\\\"name\\\":\\\"Via San Pietro\\\",\\\"oneway\\\":\\\"yes\\\",\\\"oneway:bicycle\\\":\\\"no\\\",\\\"surface\\\":\\\"sett\\\"}\",\"{\\\"access\\\":\\\"destination\\\",\\\"bicycle\\\":\\\"yes\\\",\\\"foot\\\":\\\"yes\\\",\\\"highway\\\":\\\"residential\\\",\\\"lanes\\\":\\\"1\\\",\\\"lit\\\":\\\"yes\\\",\\\"name\\\":\\\"Piazza Santa Maria Maggiore\\\",\\\"oneway\\\":\\\"yes\\\",\\\"oneway:bicycle\\\":\\\"no\\\",\\\"surface\\\":\\\"cobblestone\\\"}\",\"{\\\"access\\\":\\\"destination\\\",\\\"bicycle\\\":\\\"yes\\\",\\\"foot\\\":\\\"yes\\\",\\\"highway\\\":\\\"residential\\\",\\\"lanes\\\":\\\"1\\\",\\\"lit\\\":\\\"yes\\\",\\\"name\\\":\\\"Piazza del Duomo\\\",\\\"name:de\\\":\\\"Domplatz\\\",\\\"oneway\\\":\\\"yes\\\",\\\"oneway:bicycle\\\":\\\"no\\\",\\\"surface\\\":\\\"sett\\\"}\",\"{\\\"access\\\":\\\"destination\\\",\\\"bicycle\\\":\\\"yes\\\",\\\"foot\\\":\\\"yes\\\",\\\"highway\\\":\\\"residential\\\",\\\"lanes\\\":\\\"1\\\",\\\"lit\\\":\\\"yes\\\",\\\"name\\\":\\\"Piazza delle Erbe\\\",\\\"oneway\\\":\\\"yes\\\",\\\"oneway:bicycle\\\":\\\"no\\\",\\\"surface\\\":\\\"sett\\\"}\",\"{\\\"access\\\":\\\"destination\\\",\\\"bicycle\\\":\\\"yes\\\",\\\"foot\\\":\\\"yes\\\",\\\"highway\\\":\\\"residential\\\",\\\"lanes\\\":\\\"1\\\",\\\"lit\\\":\\\"yes\\\",\\\"name\\\":\\\"Via Andrea Pozzo\\\",\\\"oneway\\\":\\\"yes\\\",\\\"oneway:bicycle\\\":\\\"no\\\",\\\"parking:lane:both\\\":\\\"no_parking\\\",\\\"surface\\\":\\\"cobblestone\\\"}\",\"{\\\"access\\\":\\\"destination\\\",\\\"bicycle\\\":\\\"yes\\\",\\\"foot\\\":\\\"yes\\\",\\\"highway\\\":\\\"residential\\\",\\\"lanes\\\":\\\"1\\\",\\\"lit\\\":\\\"yes\\\",\\\"name\\\":\\\"Via Giannantonio Manci\\\",\\\"old_name\\\":\\\"Via Longa\\\",\\\"oneway\\\":\\\"yes\\\",\\\"oneway:bicycle\\\":\\\"no\\\",\\\"surface\\\":\\\"sett\\\"}\",\"{\\\"access\\\":\\\"destination\\\",\\\"bicycle\\\":\\\"yes\\\",\\\"foot\\\":\\\"yes\\\",\\\"highway\\\":\\\"residential\\\",\\\"lanes\\\":\\\"1\\\",\\\"lit\\\":\\\"yes\\\",\\\"name\\\":\\\"Via Mantova\\\",\\\"oneway\\\":\\\"yes\\\",\\\"oneway:bicycle\\\":\\\"no\\\",\\\"surface\\\":\\\"asphalt\\\"}\",\"{\\\"access\\\":\\\"destination\\\",\\\"bicycle\\\":\\\"yes\\\",\\\"foot\\\":\\\"yes\\\",\\\"highway\\\":\\\"residential\\\",\\\"lanes\\\":\\\"1\\\",\\\"lit\\\":\\\"yes\\\",\\\"name\\\":\\\"Via Mantova\\\",\\\"oneway\\\":\\\"yes\\\",\\\"oneway:bicycle\\\":\\\"no\\\",\\\"surface\\\":\\\"sett\\\"}\",\"{\\\"access\\\":\\\"destination\\\",\\\"bicycle\\\":\\\"yes\\\",\\\"foot\\\":\\\"yes\\\",\\\"highway\\\":\\\"residential\\\",\\\"lanes\\\":\\\"1\\\",\\\"lit\\\":\\\"yes\\\",\\\"name\\\":\\\"Via Rodolfo Belenzani\\\",\\\"old_name\\\":\\\"Via Larga\\\",\\\"oneway\\\":\\\"yes\\\",\\\"oneway:bicycle\\\":\\\"no\\\",\\\"short_name\\\":\\\"Via Belenzani\\\",\\\"surface\\\":\\\"sett\\\"}\",\"{\\\"access\\\":\\\"destination\\\",\\\"bicycle\\\":\\\"yes\\\",\\\"foot\\\":\\\"yes\\\",\\\"highway\\\":\\\"residential\\\",\\\"lanes\\\":\\\"1\\\",\\\"lit\\\":\\\"yes\\\",\\\"name\\\":\\\"Via Santissima Trinitá\\\",\\\"oneway\\\":\\\"yes\\\",\\\"oneway:bicycle\\\":\\\"no\\\",\\\"surface\\\":\\\"sett\\\"}\",\"{\\\"access\\\":\\\"destination\\\",\\\"bicycle\\\":\\\"yes\\\",\\\"foot\\\":\\\"yes\\\",\\\"highway\\\":\\\"residential\\\",\\\"lanes\\\":\\\"1\\\",\\\"lit\\\":\\\"yes\\\",\\\"name\\\":\\\"Via Vittorio Alfieri\\\",\\\"oneway\\\":\\\"yes\\\",\\\"oneway:bicycle\\\":\\\"no\\\",\\\"parking:lane:both\\\":\\\"no_parking\\\",\\\"surface\\\":\\\"paving_stones\\\"}\",\"{\\\"access\\\":\\\"destination\\\",\\\"bicycle\\\":\\\"yes\\\",\\\"foot\\\":\\\"yes\\\",\\\"highway\\\":\\\"residential\\\",\\\"lanes\\\":\\\"1\\\",\\\"lit\\\":\\\"yes\\\",\\\"name\\\":\\\"Via delle Orfane\\\",\\\"oneway\\\":\\\"yes\\\",\\\"oneway:bicycle\\\":\\\"no\\\",\\\"surface\\\":\\\"cobblestone\\\"}\",\"{\\\"access\\\":\\\"destination\\\",\\\"bicycle\\\":\\\"yes\\\",\\\"foot\\\":\\\"yes\\\",\\\"highway\\\":\\\"residential\\\",\\\"lanes\\\":\\\"1\\\",\\\"maxspeed\\\":\\\"50\\\",\\\"name\\\":\\\"Via Galileo Galilei\\\",\\\"oneway\\\":\\\"yes\\\",\\\"oneway:bicycle\\\":\\\"no\\\",\\\"surface\\\":\\\"cobblestone\\\"}\",\"{\\\"access\\\":\\\"destination\\\",\\\"bicycle\\\":\\\"yes\\\",\\\"foot\\\":\\\"yes\\\",\\\"highway\\\":\\\"residential\\\",\\\"lanes\\\":\\\"1\\\",\\\"name\\\":\\\"Largo Giosuè Carducci\\\",\\\"oneway\\\":\\\"yes\\\",\\\"oneway:bicycle\\\":\\\"no\\\",\\\"surface\\\":\\\"sett\\\"}\",\"{\\\"access\\\":\\\"destination\\\",\\\"bicycle\\\":\\\"yes\\\",\\\"foot\\\":\\\"yes\\\",\\\"highway\\\":\\\"residential\\\",\\\"lanes\\\":\\\"1\\\",\\\"name\\\":\\\"Piazza Santa Maria Maggiore\\\",\\\"oneway\\\":\\\"yes\\\",\\\"oneway:bicycle\\\":\\\"no\\\",\\\"surface\\\":\\\"cobblestone\\\"}\",\"{\\\"access\\\":\\\"destination\\\",\\\"bicycle\\\":\\\"yes\\\",\\\"foot\\\":\\\"yes\\\",\\\"highway\\\":\\\"residential\\\",\\\"lanes\\\":\\\"1\\\",\\\"name\\\":\\\"Piazza Santa Maria Maggiore\\\",\\\"oneway\\\":\\\"yes\\\",\\\"oneway:bicycle\\\":\\\"no\\\",\\\"surface\\\":\\\"sett\\\"}\",\"{\\\"access\\\":\\\"destination\\\",\\\"bicycle\\\":\\\"yes\\\",\\\"foot\\\":\\\"yes\\\",\\\"highway\\\":\\\"residential\\\",\\\"lanes\\\":\\\"1\\\",\\\"name\\\":\\\"Via Calepina\\\",\\\"oneway\\\":\\\"yes\\\",\\\"oneway:bicycle\\\":\\\"no\\\",\\\"surface\\\":\\\"cobblestone\\\"}\",\"{\\\"access\\\":\\\"destination\\\",\\\"bicycle\\\":\\\"yes\\\",\\\"foot\\\":\\\"yes\\\",\\\"highway\\\":\\\"residential\\\",\\\"lanes\\\":\\\"1\\\",\\\"name\\\":\\\"Via Calepina\\\",\\\"oneway\\\":\\\"yes\\\",\\\"oneway:bicycle\\\":\\\"no\\\",\\\"surface\\\":\\\"paved\\\"}\",\"{\\\"access\\\":\\\"destination\\\",\\\"bicycle\\\":\\\"yes\\\",\\\"foot\\\":\\\"yes\\\",\\\"highway\\\":\\\"residential\\\",\\\"lanes\\\":\\\"1\\\",\\\"name\\\":\\\"Via Camillo Benso Cavour\\\",\\\"oneway\\\":\\\"yes\\\",\\\"oneway:bicycle\\\":\\\"no\\\",\\\"shortest_name\\\":\\\"Via Cavour\\\",\\\"surface\\\":\\\"cobblestone\\\"}\",\"{\\\"access\\\":\\\"destination\\\",\\\"bicycle\\\":\\\"yes\\\",\\\"foot\\\":\\\"yes\\\",\\\"highway\\\":\\\"residential\\\",\\\"lanes\\\":\\\"1\\\",\\\"name\\\":\\\"Via Carlo Dordi\\\",\\\"oneway\\\":\\\"yes\\\",\\\"oneway:bicycle\\\":\\\"no\\\",\\\"surface\\\":\\\"paved\\\"}\",\"{\\\"access\\\":\\\"destination\\\",\\\"bicycle\\\":\\\"yes\\\",\\\"foot\\\":\\\"yes\\\",\\\"highway\\\":\\\"residential\\\",\\\"lanes\\\":\\\"1\\\",\\\"name\\\":\\\"Via Roccabruna\\\",\\\"oneway\\\":\\\"yes\\\",\\\"oneway:bicycle\\\":\\\"no\\\",\\\"surface\\\":\\\"paved\\\"}\",\"{\\\"access\\\":\\\"destination\\\",\\\"bicycle\\\":\\\"yes\\\",\\\"foot\\\":\\\"yes\\\",\\\"highway\\\":\\\"residential\\\",\\\"lanes\\\":\\\"1\\\",\\\"name\\\":\\\"Via Roma\\\",\\\"old_name\\\":\\\"Via Longa\\\",\\\"oneway\\\":\\\"yes\\\",\\\"oneway:bicycle\\\":\\\"no\\\",\\\"surface\\\":\\\"cobblestone\\\"}\",\"{\\\"access\\\":\\\"destination\\\",\\\"bicycle\\\":\\\"yes\\\",\\\"foot\\\":\\\"yes\\\",\\\"highway\\\":\\\"residential\\\",\\\"lanes\\\":\\\"1\\\",\\\"name\\\":\\\"Via Santa Maria Maddalena\\\",\\\"oneway\\\":\\\"yes\\\",\\\"oneway:bicycle\\\":\\\"no\\\",\\\"surface\\\":\\\"sett\\\"}\",\"{\\\"access\\\":\\\"destination\\\",\\\"bicycle\\\":\\\"yes\\\",\\\"foot\\\":\\\"yes\\\",\\\"highway\\\":\\\"residential\\\",\\\"lanes\\\":\\\"1\\\",\\\"name\\\":\\\"Via Santissima Trinitá\\\",\\\"oneway\\\":\\\"yes\\\",\\\"oneway:bicycle\\\":\\\"no\\\",\\\"surface\\\":\\\"paved\\\"}\",\"{\\\"access\\\":\\\"destination\\\",\\\"bicycle\\\":\\\"yes\\\",\\\"foot\\\":\\\"yes\\\",\\\"highway\\\":\\\"residential\\\",\\\"lanes\\\":\\\"1\\\",\\\"name\\\":\\\"Via Santissima Trinitá\\\",\\\"oneway\\\":\\\"yes\\\",\\\"oneway:bicycle\\\":\\\"no\\\",\\\"surface\\\":\\\"sett\\\"}\",\"{\\\"access\\\":\\\"destination\\\",\\\"bicycle\\\":\\\"yes\\\",\\\"foot\\\":\\\"yes\\\",\\\"highway\\\":\\\"residential\\\",\\\"lanes\\\":\\\"1\\\",\\\"name\\\":\\\"Vicolo del Liceo\\\",\\\"oneway\\\":\\\"yes\\\",\\\"oneway:bicycle\\\":\\\"no\\\",\\\"surface\\\":\\\"cobblestone\\\"}\",\"{\\\"access\\\":\\\"destination\\\",\\\"bicycle\\\":\\\"yes\\\",\\\"foot\\\":\\\"yes\\\",\\\"highway\\\":\\\"residential\\\",\\\"lanes\\\":\\\"1\\\",\\\"oneway\\\":\\\"yes\\\",\\\"oneway:bicycle\\\":\\\"no\\\"}\",\"{\\\"access\\\":\\\"destination\\\",\\\"bicycle\\\":\\\"yes\\\",\\\"foot\\\":\\\"yes\\\",\\\"highway\\\":\\\"residential\\\",\\\"lit\\\":\\\"yes\\\",\\\"maxspeed\\\":\\\"50\\\",\\\"name\\\":\\\"Via Dietro Le Mura B\\\",\\\"oneway\\\":\\\"yes\\\",\\\"surface\\\":\\\"cubes\\\"}\",\"{\\\"access\\\":\\\"destination\\\",\\\"bicycle\\\":\\\"yes\\\",\\\"foot\\\":\\\"yes\\\",\\\"highway\\\":\\\"residential\\\",\\\"lit\\\":\\\"yes\\\",\\\"name\\\":\\\"Via Roma\\\",\\\"old_name\\\":\\\"Via Longa\\\",\\\"oneway\\\":\\\"yes\\\",\\\"oneway:bicycle\\\":\\\"no\\\",\\\"surface\\\":\\\"sett\\\"}\",\"{\\\"access\\\":\\\"destination\\\",\\\"bicycle\\\":\\\"yes\\\",\\\"foot\\\":\\\"yes\\\",\\\"highway\\\":\\\"residential\\\",\\\"name\\\":\\\"Via Santa Maria Maddalena\\\",\\\"oneway:bicycle\\\":\\\"no\\\",\\\"surface\\\":\\\"sett\\\"}\",\"{\\\"access\\\":\\\"destination\\\",\\\"bicycle\\\":\\\"yes\\\",\\\"foot\\\":\\\"yes\\\",\\\"highway\\\":\\\"service\\\",\\\"lanes\\\":\\\"1\\\",\\\"name\\\":\\\"Prima Androna di Borgo Nuovo\\\",\\\"oneway\\\":\\\"yes\\\",\\\"oneway:bicycle\\\":\\\"no\\\",\\\"surface\\\":\\\"cobblestone\\\"}\",\"{\\\"access\\\":\\\"destination\\\",\\\"bicycle\\\":\\\"yes\\\",\\\"foot\\\":\\\"yes\\\",\\\"highway\\\":\\\"service\\\",\\\"lanes\\\":\\\"1\\\",\\\"name\\\":\\\"Seconda Androna di Borgo Nuovo\\\",\\\"oneway\\\":\\\"yes\\\",\\\"oneway:bicycle\\\":\\\"no\\\",\\\"surface\\\":\\\"cobblestone\\\"}\",\"{\\\"access\\\":\\\"destination\\\",\\\"bicycle\\\":\\\"yes\\\",\\\"foot\\\":\\\"yes\\\",\\\"highway\\\":\\\"service\\\",\\\"lanes\\\":\\\"1\\\",\\\"oneway\\\":\\\"no\\\",\\\"oneway:bicycle\\\":\\\"no\\\",\\\"surface\\\":\\\"cobblestone\\\"}\",\"{\\\"access\\\":\\\"destination\\\",\\\"bicycle\\\":\\\"yes\\\",\\\"foot\\\":\\\"yes\\\",\\\"highway\\\":\\\"service\\\",\\\"lanes\\\":\\\"1\\\",\\\"oneway\\\":\\\"yes\\\",\\\"surface\\\":\\\"cobblestone\\\"}\",\"{\\\"access\\\":\\\"destination\\\",\\\"bicycle\\\":\\\"yes\\\",\\\"foot\\\":\\\"yes\\\",\\\"highway\\\":\\\"service\\\",\\\"maxspeed\\\":\\\"20\\\",\\\"name\\\":\\\"Via dei Consolati\\\"}\",\"{\\\"access\\\":\\\"destination\\\",\\\"bicycle\\\":\\\"yes\\\",\\\"foot\\\":\\\"yes\\\",\\\"highway\\\":\\\"service\\\",\\\"maxspeed\\\":\\\"20\\\",\\\"name\\\":\\\"Via per Fontanasanta\\\"}\",\"{\\\"access\\\":\\\"destination\\\",\\\"bicycle\\\":\\\"yes\\\",\\\"foot\\\":\\\"yes\\\",\\\"highway\\\":\\\"service\\\",\\\"maxspeed\\\":\\\"20\\\"}\",\"{\\\"access\\\":\\\"destination\\\",\\\"bicycle\\\":\\\"yes\\\",\\\"foot\\\":\\\"yes\\\",\\\"highway\\\":\\\"service\\\"}\",\"{\\\"access\\\":\\\"destination\\\",\\\"bicycle\\\":\\\"yes\\\",\\\"highway\\\":\\\"residential\\\",\\\"lanes\\\":\\\"1\\\",\\\"maxspeed\\\":\\\"50\\\",\\\"name\\\":\\\"Via Calepina\\\",\\\"oneway\\\":\\\"yes\\\",\\\"oneway:bicycle\\\":\\\"no\\\",\\\"surface\\\":\\\"asphalt\\\"}\",\"{\\\"access\\\":\\\"destination\\\",\\\"bicycle\\\":\\\"yes\\\",\\\"highway\\\":\\\"residential\\\",\\\"lanes\\\":\\\"1\\\",\\\"maxspeed\\\":\\\"50\\\",\\\"name\\\":\\\"Via Calepina\\\",\\\"oneway\\\":\\\"yes\\\",\\\"oneway:bicycle\\\":\\\"no\\\",\\\"surface\\\":\\\"paved\\\"}\",\"{\\\"access\\\":\\\"destination\\\",\\\"bicycle\\\":\\\"yes\\\",\\\"highway\\\":\\\"residential\\\",\\\"lanes\\\":\\\"1\\\",\\\"maxspeed\\\":\\\"50\\\",\\\"name\\\":\\\"Via Mantova\\\",\\\"oneway\\\":\\\"yes\\\",\\\"oneway:bicycle\\\":\\\"no\\\",\\\"surface\\\":\\\"asphalt\\\"}\",\"{\\\"access\\\":\\\"destination\\\",\\\"bicycle\\\":\\\"yes\\\",\\\"highway\\\":\\\"unclassified\\\",\\\"name\\\":\\\"Via al Torrione\\\",\\\"oneway:bicycle\\\":\\\"no\\\",\\\"surface\\\":\\\"paved\\\"}\",\"{\\\"access\\\":\\\"destination\\\",\\\"highway\\\":\\\"footway\\\"}\",\"{\\\"access\\\":\\\"destination\\\",\\\"highway\\\":\\\"residential\\\",\\\"lane_markings\\\":\\\"no\\\",\\\"lit\\\":\\\"yes\\\",\\\"maxheight\\\":\\\"3.2\\\",\\\"maxspeed\\\":\\\"50\\\",\\\"name\\\":\\\"Via Dietro Le Mura B\\\",\\\"oneway\\\":\\\"yes\\\",\\\"surface\\\":\\\"sett\\\",\\\"tunnel\\\":\\\"building_passage\\\"}\",\"{\\\"access\\\":\\\"destination\\\",\\\"highway\\\":\\\"residential\\\",\\\"lit\\\":\\\"yes\\\",\\\"maxspeed\\\":\\\"50\\\",\\\"name\\\":\\\"Via Dietro Le Mura B\\\",\\\"oneway\\\":\\\"yes\\\",\\\"surface\\\":\\\"cubes\\\"}\",\"{\\\"access\\\":\\\"destination\\\",\\\"highway\\\":\\\"residential\\\",\\\"lit\\\":\\\"yes\\\",\\\"name\\\":\\\"Via della Ca' dei Gai\\\",\\\"surface\\\":\\\"asphalt\\\"}\",\"{\\\"access\\\":\\\"destination\\\",\\\"highway\\\":\\\"residential\\\",\\\"name\\\":\\\"Lungadige Marco Apuleio\\\",\\\"surface\\\":\\\"asphalt\\\"}\",\"{\\\"access\\\":\\\"destination\\\",\\\"highway\\\":\\\"service\\\",\\\"layer\\\":\\\"-1\\\",\\\"oneway\\\":\\\"yes\\\",\\\"surface\\\":\\\"asphalt\\\",\\\"tunnel\\\":\\\"yes\\\"}\",\"{\\\"access\\\":\\\"destination\\\",\\\"highway\\\":\\\"service\\\",\\\"maxspeed\\\":\\\"20\\\",\\\"oneway\\\":\\\"yes\\\",\\\"service\\\":\\\"parking_aisle\\\"}\",\"{\\\"access\\\":\\\"destination\\\",\\\"highway\\\":\\\"service\\\",\\\"oneway\\\":\\\"yes\\\",\\\"surface\\\":\\\"cobblestone\\\"}\",\"{\\\"access\\\":\\\"destination\\\",\\\"highway\\\":\\\"service\\\",\\\"service\\\":\\\"driveway\\\"}\",\"{\\\"access\\\":\\\"destination\\\",\\\"highway\\\":\\\"service\\\",\\\"service\\\":\\\"parking_aisle\\\",\\\"surface\\\":\\\"asphalt\\\"}\",\"{\\\"access\\\":\\\"destination\\\",\\\"highway\\\":\\\"service\\\",\\\"surface\\\":\\\"earth\\\"}\",\"{\\\"access\\\":\\\"destination\\\",\\\"highway\\\":\\\"service\\\"}\",\"{\\\"access\\\":\\\"destination\\\",\\\"highway\\\":\\\"track\\\",\\\"mtb:scale\\\":\\\"1\\\",\\\"surface\\\":\\\"ground\\\",\\\"tracktype\\\":\\\"grade4\\\"}\",\"{\\\"access\\\":\\\"destination\\\",\\\"highway\\\":\\\"track\\\",\\\"tracktype\\\":\\\"grade4\\\"}\",\"{\\\"access\\\":\\\"destination\\\",\\\"highway\\\":\\\"unclassified\\\",\\\"name\\\":\\\"Strada del Dos Gariol\\\"}\",\"{\\\"access\\\":\\\"forestry\\\",\\\"alt_name\\\":\\\"Strada Rifugio del Calisio\\\",\\\"bicycle\\\":\\\"yes\\\",\\\"foot\\\":\\\"yes\\\",\\\"highway\\\":\\\"track\\\",\\\"mtb:scale\\\":\\\"1\\\",\\\"name\\\":\\\"Strada de Mez\\\"}\",\"{\\\"access\\\":\\\"forestry\\\",\\\"alt_name\\\":\\\"Strada Rifugio del Calisio\\\",\\\"bicycle\\\":\\\"yes\\\",\\\"foot\\\":\\\"yes\\\",\\\"highway\\\":\\\"track\\\",\\\"name\\\":\\\"Strada de Mez\\\"}\",\"{\\\"access\\\":\\\"forestry\\\",\\\"bicycle\\\":\\\"yes\\\",\\\"designation\\\":\\\"IT-TN:strada_forestale_tipo_a\\\",\\\"emergency\\\":\\\"yes\\\",\\\"foot\\\":\\\"yes\\\",\\\"forestry\\\":\\\"yes\\\",\\\"highway\\\":\\\"track\\\",\\\"horse\\\":\\\"yes\\\",\\\"motor_vehicle\\\":\\\"forestry\\\",\\\"name\\\":\\\"Strada forestale Val Granda\\\",\\\"tracktype\\\":\\\"grade2\\\"}\",\"{\\\"access\\\":\\\"forestry\\\",\\\"bicycle\\\":\\\"yes\\\",\\\"foot\\\":\\\"yes\\\",\\\"highway\\\":\\\"path\\\",\\\"incline\\\":\\\"up\\\",\\\"mtb:scale\\\":\\\"1\\\",\\\"mtb:scale:uphill\\\":\\\"1\\\",\\\"surface\\\":\\\"ground\\\",\\\"width\\\":\\\"1\\\"}\",\"{\\\"access\\\":\\\"forestry\\\",\\\"bicycle\\\":\\\"yes\\\",\\\"foot\\\":\\\"yes\\\",\\\"highway\\\":\\\"track\\\",\\\"mtb:scale\\\":\\\"1\\\",\\\"mtb:scale:uphill\\\":\\\"1\\\",\\\"source\\\":\\\"Yahoo\\\",\\\"tracktype\\\":\\\"grade3\\\"}\",\"{\\\"access\\\":\\\"forestry\\\",\\\"bicycle\\\":\\\"yes\\\",\\\"foot\\\":\\\"yes\\\",\\\"highway\\\":\\\"track\\\",\\\"mtb:scale\\\":\\\"1\\\",\\\"mtb:scale:uphill\\\":\\\"1\\\",\\\"tracktype\\\":\\\"grade3\\\"}\",\"{\\\"access\\\":\\\"forestry\\\",\\\"bicycle\\\":\\\"yes\\\",\\\"foot\\\":\\\"yes\\\",\\\"highway\\\":\\\"track\\\",\\\"mtb:scale\\\":\\\"1\\\",\\\"mtb:scale:uphill\\\":\\\"2\\\",\\\"tracktype\\\":\\\"grade3\\\"}\",\"{\\\"access\\\":\\\"forestry\\\",\\\"bicycle\\\":\\\"yes\\\",\\\"foot\\\":\\\"yes\\\",\\\"highway\\\":\\\"track\\\",\\\"mtb:scale\\\":\\\"1\\\",\\\"mtb:scale:uphill\\\":\\\"2\\\"}\",\"{\\\"access\\\":\\\"forestry\\\",\\\"bicycle\\\":\\\"yes\\\",\\\"foot\\\":\\\"yes\\\",\\\"highway\\\":\\\"track\\\",\\\"mtb:scale\\\":\\\"1\\\"}\",\"{\\\"access\\\":\\\"forestry\\\",\\\"bicycle\\\":\\\"yes\\\",\\\"foot\\\":\\\"yes\\\",\\\"highway\\\":\\\"track\\\",\\\"name\\\":\\\"Strada della Flora\\\",\\\"ref\\\":\\\"401\\\",\\\"surface\\\":\\\"gravel\\\"}\",\"{\\\"access\\\":\\\"forestry\\\",\\\"bicycle\\\":\\\"yes\\\",\\\"foot\\\":\\\"yes\\\",\\\"highway\\\":\\\"track\\\",\\\"name\\\":\\\"Strada della Flora\\\",\\\"surface\\\":\\\"gravel\\\",\\\"tracktype\\\":\\\"grade2\\\"}\",\"{\\\"access\\\":\\\"forestry\\\",\\\"bicycle\\\":\\\"yes\\\",\\\"foot\\\":\\\"yes\\\",\\\"highway\\\":\\\"track\\\",\\\"smoothness\\\":\\\"horrible\\\",\\\"tracktype\\\":\\\"grade3\\\"}\",\"{\\\"access\\\":\\\"forestry\\\",\\\"bicycle\\\":\\\"yes\\\",\\\"foot\\\":\\\"yes\\\",\\\"highway\\\":\\\"track\\\",\\\"source\\\":\\\"Yahoo\\\"}\",\"{\\\"access\\\":\\\"forestry\\\",\\\"bicycle\\\":\\\"yes\\\",\\\"foot\\\":\\\"yes\\\",\\\"highway\\\":\\\"track\\\",\\\"tracktype\\\":\\\"grade3\\\"}\",\"{\\\"access\\\":\\\"forestry\\\",\\\"bicycle\\\":\\\"yes\\\",\\\"foot\\\":\\\"yes\\\",\\\"highway\\\":\\\"track\\\"}\",\"{\\\"access\\\":\\\"forestry\\\",\\\"bicycle\\\":\\\"yes\\\",\\\"highway\\\":\\\"track\\\"}\",\"{\\\"access\\\":\\\"forestry\\\",\\\"embankment\\\":\\\"yes\\\",\\\"highway\\\":\\\"path\\\",\\\"motorcar\\\":\\\"no\\\",\\\"motorcycle\\\":\\\"no\\\",\\\"mtb:scale\\\":\\\"1\\\",\\\"surface\\\":\\\"ground\\\",\\\"tracktype\\\":\\\"grade2\\\",\\\"width\\\":\\\"2\\\"}\"]},{\"attribute\": \"type\",\"count\": 1,\"type\": \"string\",\"values\": [\"way\"]}]}]}}"
}
